shushuo
