Metadata-Version: 1.0
Name: shushuo
Version: 0.0.8
Summary: Python Client for ShuShuo.com
Home-page: https://github.com/shushuo/shushuo.py
Author: Kerwin
Author-email: piaoyuankui@gmail.com
License: UNKNOWN
Platform: UNKNOWN
